{
    "questions": {
        "og": {
          "How many beard seconds tall is the Empire State Building?": [[9], ["1454", "ft", "1", "Beard Second", "1454", "2.42*10^9"], ["1", "Empire State Building", "0.0000006", "ft", "0.0000006"]],
          "If you traveled 1 foot per second how many centuries would it take you to reach the moon?": [[0], ["1", "miles", "1", "ft", "3000000000", "second", "3000000000", "2.3*10^0"], ["238900", "distance to moon", "5280", "miles", "1", "century", "1261392000"]],
          "How many sheets of paper would it take to fill a Boeing 747?": [[8], ["1", "Boeing 747", "0.3553", "in^3", "0.000578704", "ft^3", "0.0002056135312", "6.5*10^-9"], ["31,285", "ft^3", "1", "sheet of paper", "1", "cubic inches", "31285"]], 
          "How many galaxies would fit inside a thimble?": [[-56], ["1", "galaxy", "1", "lightyear^3", "1", "volume of thimble", "16.3871", "cm^3", "16.3871", "1.10^10^-56"], ["100000000", "lightyears^3", "2.9*10^49", "in^3", "0.5", "cm^3", "1", "in^3", "1.49*10^57"]],
          "How long would it take for a ray of light to travel around the Earth in minutes?": [[-3], ["1", "sec", "25000", "miles", "1609", "meters", "1", "min", "40225000", "2*10^-3"], ["300000000", "meters", "1", "circumference of Earth", "1", "mile", "60", "sec", "18000000000"]], 
          "If a penny fell from the top of the Empire State Building how many decades would it take to hit the ground?": [[-5], ["1", "Eiffel tower", "60", "miles", "1", "decade", "1609.34", "meters", "96560.4", "5.6*10^-5"], ["330", "meters", "1", "hour", "5200000", "minuets", "1", "mile", "1716000000"]],
          "How many rotations of a bike tire would occure if you were to bike from Seattle to New York?": [[6], ["1", "tire circumference", "4645", "km", "1000000", "mm", "4645010000", "2*10^6"], ["2200", "mm", "1", "distance from Seattle to NY", "1", "km", "2200"]],
          "How large is a grain of sand measured in the volume of average human adult males?": [[-8], ["0.00947", "mm^3", "1", "Average human male", "1", "cm^3", "0.00947", "1*10^8"], ["1", "grain of sand", "1000", "cm^3", "1000", "mm^3", "1000000"]]
        }
    },
    "sources": {
        "og": {
            "link": "https://docs.google.com/spreadsheets/d/1fhhC9v9RG0n9955AW1duTIAE-rBmjSig5OHZK53azgI/edit?usp=sharing",
            "author": "Soam Norlie",
            "date": "May 1, 2023"
        
        }
    }

}
